webwhatsapi/consts.py
webwhatsapi/helper.py
webwhatsapi/async_driver.py
webwhatsapi/wapi_js_wrapper.py
webwhatsapi/__init__.py
webwhatsapi/__pycache__/__init__.cpython-36.pyc
webwhatsapi/__pycache__/helper.cpython-36.pyc
webwhatsapi/__pycache__/wapi_js_wrapper.cpython-36.pyc
webwhatsapi/js/.eslintrc.json
webwhatsapi/js/.gitignore
webwhatsapi/js/wapi.js
webwhatsapi/objects/__init__.py
webwhatsapi/objects/chat.py
webwhatsapi/objects/contact.py
webwhatsapi/objects/message.py
webwhatsapi/objects/whatsapp_object.py
webwhatsapi/objects/__pycache__/__init__.cpython-36.pyc
webwhatsapi/objects/__pycache__/chat.cpython-36.pyc
webwhatsapi/objects/__pycache__/contact.cpython-36.pyc
webwhatsapi/objects/__pycache__/message.cpython-36.pyc
webwhatsapi/objects/__pycache__/whatsapp_object.cpython-36.pyc
webwhatsapi-2.0.4.dist-info/top_level.txt
webwhatsapi-2.0.4.dist-info/METADATA
webwhatsapi-2.0.4.dist-info/DESCRIPTION.rst
webwhatsapi-2.0.4.dist-info/metadata.json
webwhatsapi-2.0.4.dist-info/WHEEL
webwhatsapi-2.0.4.dist-info/RECORD
