Metadata-Version: 2.0
Name: webwhatsapi
Version: 2.0.4
Summary: A python interface for Whatsapp Web
Home-page: https://github.com/mukulhase/WhatsAPI
Author: Mukul Hase
Author-email: mukulhase@gmail.com
License: MIT
Download-URL: https://github.com/mukulhase/WhatsAPI/archive/2.0.4.tar.gz
Keywords: Whatsapp Chat Bot Chatbot Selenium Web Whatsapp API
Platform: UNKNOWN
Classifier: Development Status :: 4 - Beta
Classifier: Intended Audience :: Developers
Classifier: Topic :: Communications :: Chat
Classifier: License :: OSI Approved :: MIT License
Classifier: Programming Language :: Python :: 2.7
Classifier: Programming Language :: Python :: 3.6
Requires-Dist: python-dateutil (>=2.6.0)
Requires-Dist: selenium (>=3.4.3)
Requires-Dist: six (>=1.10.0)
Requires-Dist: python-axolotl
Requires-Dist: cryptography
